{
  "editor:toggle-bullet-list": [
    {
      "modifiers": [
        "Mod"
      ],
      "key": "L"
    }
  ],
  "editor:toggle-checklist-status": [],
  "editor:toggle-blockquote": [
    {
      "modifiers": [
        "Mod"
      ],
      "key": "Q"
    }
  ],
  "obsidian-regex-replace:obsidian-regex-replace": [
    {
      "modifiers": [
        "Mod",
        "Shift"
      ],
      "key": "H"
    }
  ],
  "text-finder:text-finder-show-find-and-replace": [
    {
      "modifiers": [
        "Mod",
        "Shift"
      ],
      "key": "H"
    }
  ]
}